looptime/.gitignore
looptime/__init__.py
looptime/_version.py
looptime/chronometers.py
looptime/enabler.py
looptime/loops.py
looptime/math.py
looptime/patchers.py
looptime/plugin.py
looptime/py.typed
looptime/timeproxies.py
looptime-0.6.dist-info/licenses/LICENSE
looptime-0.6.dist-info/METADATA
looptime-0.6.dist-info/WHEEL
looptime-0.6.dist-info/entry_points.txt
looptime-0.6.dist-info/top_level.txt
looptime-0.6.dist-info/RECORD
