Metadata-Version: 2.4
Name: looptime
Version: 0.6
Summary: Fast-forward asyncio event loop time (in tests)
Author-email: Sergey Vasilyev <nolar@nolar.info>
Maintainer-email: Sergey Vasilyev <nolar@nolar.info>
License-Expression: MIT
Project-URL: homepage, https://github.com/nolar/looptime
Project-URL: repository, https://github.com/nolar/looptime
Project-URL: documentation, https://github.com/nolar/looptime
Keywords: asyncio,event loop,time,python,pytest
Classifier: Intended Audience :: Developers
Classifier: Operating System :: OS Independent
Classifier: Framework :: AsyncIO
Classifier: Framework :: Pytest
Classifier: Framework :: aiohttp
Classifier: Programming Language :: Python
Classifier: Programming Language :: Python :: 3
Classifier: Programming Language :: Python :: 3.10
Classifier: Programming Language :: Python :: 3.11
Classifier: Programming Language :: Python :: 3.12
Classifier: Programming Language :: Python :: 3.13
Classifier: Programming Language :: Python :: 3.14
Classifier: Programming Language :: Python :: 3 :: Only
Classifier: Programming Language :: Python :: Implementation :: CPython
Classifier: Programming Language :: Python :: Implementation :: PyPy
Classifier: Topic :: Software Development :: Testing
Classifier: Topic :: Software Development :: Libraries
Classifier: Typing :: Typed
Requires-Python: >=3.10
License-File: LICENSE
Dynamic: license-file
